LICENSE
README.md
setup.cfg
setup.py
lib/vsc/__init__.py
lib/vsc/utils/__init__.py
lib/vsc/utils/availability.py
lib/vsc/utils/cache.py
lib/vsc/utils/fs_store.py
lib/vsc/utils/graphyte.py
lib/vsc/utils/lock.py
lib/vsc/utils/nagios.py
lib/vsc/utils/pickle_files.py
lib/vsc/utils/rest_oauth.py
lib/vsc/utils/script_tools.py
lib/vsc/utils/timestamp.py
lib/vsc/utils/timestamp_pid_lockfile.py
lib/vsc_utils.egg-info/PKG-INFO
lib/vsc_utils.egg-info/SOURCES.txt
lib/vsc_utils.egg-info/dependency_links.txt
lib/vsc_utils.egg-info/namespace_packages.txt
lib/vsc_utils.egg-info/not-zip-safe
lib/vsc_utils.egg-info/requires.txt
lib/vsc_utils.egg-info/top_level.txt