Metadata-Version: 2.1
Name: vsc-utils
Version: 2.2.8
Summary: Common tools used within our organization. These tools live in the vsc.utils namespace, toghether with the tools from vsc-base.
Home-page: https://github.com/hpcugent/vsc-utils
Download-URL: 
Author: Andy Georges;Stijn De Weirdt
Author-email: andy.georges@ugent.be, stijn.deweirdt@ugent.be
Maintainer: Andy Georges;Stijn De Weirdt
Maintainer-email: andy.georges@ugent.be, stijn.deweirdt@ugent.be
License: LGPLv2+
Classifier: License :: OSI Approved :: GNU Lesser General Public License v2 or later (LGPLv2+)
License-File: LICENSE
